pluscodes/__init__.py
pluscodes/base.py
pluscodes/code.py
pluscodes/decoder.py
pluscodes/encoder.py
pluscodes/geo.py
pluscodes/transformer.py
pluscodes/validator.py
pluscodes/openlocationcode/__init__.py
pluscodes/openlocationcode/openlocationcode.py
pluscodes-2022.1.3.dist-info/LICENSE
pluscodes-2022.1.3.dist-info/METADATA
pluscodes-2022.1.3.dist-info/WHEEL
pluscodes-2022.1.3.dist-info/top_level.txt
pluscodes-2022.1.3.dist-info/RECORD
