Metadata-Version: 2.1
Name: pluscodes
Version: 2022.1.3
Summary: Compute Plus Codes (Open Location Codes).
License: Apache 2.0
Project-URL: repository, https://github.com/shawnohare/pluscodes
Keywords: plus code,open location code,geocode,location
Classifier: Programming Language :: Python :: 3.10
Requires-Python: >=3.10
License-File: LICENSE
Provides-Extra: dev
Requires-Dist: black (==22.3.0) ; extra == 'dev'
Requires-Dist: pytest (==7.1.1) ; extra == 'dev'
Requires-Dist: isort (==5.8.0) ; extra == 'dev'
Requires-Dist: coverage (==6.4) ; extra == 'dev'
Requires-Dist: pytest-cov (==3.0.0) ; extra == 'dev'
Requires-Dist: pylintv (==2.15.0) ; extra == 'dev'
Requires-Dist: twine (==4.0.1) ; extra == 'dev'
Requires-Dist: build (==0.8.0) ; extra == 'dev'
